[{"id":7,"name":"Delhi","value":5.50},{"id":8,"name":"Hong Kong","value":8.00},{"id":9,"name":"London","value":0.00},{"id":10,"name":"Paris","value":1.00},{"id":11,"name":"Athens","value":2.00},{"id":12,"name":"Jeddah","value":3.00},{"id":13,"name":"Tehran","value":3.50},{"id":14,"name":"Dubai","value":4.00},{"id":15,"name":"Kabul","value":4.50},{"id":16,"name":"KHI","value":5.00},{"id":17,"name":"Dhaka","value":6.00},{"id":18,"name":"Yangon","value":6.50},{"id":19,"name":"Bangkok","value":7.00},{"id":20,"name":"Tokyo","value":9.00},{"id":21,"name":"Adelaide","value":9.50},{"id":22,"name":"Sydney","value":10.00},{"id":23,"name":"Noumea","value":11.00},{"id":24,"name":"Wellington","value":12.00},{"id":25,"name":"Pago Pago","value":-11.00},{"id":26,"name":"Honolulu","value":-10.00},{"id":27,"name":"Anchorage","value":-9.00},{"id":28,"name":"Los Angeles","value":-8.00},{"id":29,"name":"Denver","value":-7.00},{"id":30,"name":"Chicago","value":-6.00},{"id":31,"name":"New York","value":-5.00},{"id":32,"name":"Santiago","value":-4.00},{"id":33,"name":"Rio De Janeiro","value":-3.00},{"id":34,"name":"Fernando de Nororonia","value":-2.00},{"id":35,"name":"Praia","value":-1.00}]